{"name":"Proyecto MusicTop ","tagline":"Static Page de la asignatura SYTW.","body":"\r\nproyecto\")\r\n=========\r\nProyecto : MusicTop\r\n---------\r\nAutor:  Adán Rafael López Lecuona.\r\n\r\n#Objetivo\r\n\r\nRed social dedicada a la compartición de enlaces de música, con las lista de mejores valorados. En el cuál el usuario podrá conocer a multiples amigos afines a su misma música.\r\n\r\n-------------------------------------\r\n# Enlaces de la APP \r\n\r\n### Enlace de: StaticPage\r\n[Ir a la static Page](http://xandobit.github.io/webpageSYTW.github.io/)\r\n### Enlace de: Heroku\r\n[Ir a App en Heroku](https://MusicTop.herokuapp.com/)\r\n\r\n\r\n\r\n### Enlace de Coveralls\r\n[![Coverage Status](https://coveralls.io/repos/XandoBit/MusicTop/badge.png)](https://coveralls.io/r/XandoBit/MusicTop)\r\n\r\n-------------------------------------","google":"","note":"Don't delete this file! It's used internally to help with page regeneration."}